rtl/uart_cmd.v
// rtl/uart_cmd.v
// UART command interface with counter readback
// Commands: PING (0x03), READ (0x02)
// Frame: A5 cmd addr d0 d1 chk
// Resp : 5A status addr d0 d1 chk

module uart_cmd (
    input  wire       clk,
    input  wire       rst,

    input  wire       rx_valid,
    input  wire [7:0] rx_data,

    output reg        tx_valid,
    output reg  [7:0] tx_data,
    input  wire       tx_ready
);

    // -----------------------------
    // Internal registers
    // -----------------------------
    reg [2:0] rx_count;
    reg [7:0] b0, b1, b2, b3, b4, b5;

    reg [7:0] last_status;
    reg       parser_error_seen;
    reg       last_cmd_valid;

    reg [7:0] r0, r1, r2, r3, r4, r5;
    reg [2:0] tx_count;
    reg       resp_pending;

    // Day 16: free-running counter
    reg [31:0] cycle_counter;

    // -----------------------------
    // Constants
    // -----------------------------
    localparam [7:0] SOF      = 8'hA5;
    localparam [7:0] SOF_RESP = 8'h5A;

    localparam [7:0] CMD_PING = 8'h03;
    localparam [7:0] CMD_RD   = 8'h02;

    localparam [7:0] ST_OK      = 8'h00;
    localparam [7:0] ST_BADSOF  = 8'hE1;
    localparam [7:0] ST_BADCHK  = 8'hE2;
    localparam [7:0] ST_BADCMD  = 8'hE3;
    localparam [7:0] ST_BADADDR = 8'hE4;

    localparam [15:0] REG_ID      = 16'h4B34;
    localparam [15:0] REG_VERSION = 16'h0016;

    // -----------------------------
    // Helper functions
    // -----------------------------
    function [7:0] chk;
        input [7:0] a,b,c,d,e;
        begin
            chk = a ^ b ^ c ^ d ^ e;
        end
    endfunction

    function addr_ok;
        input [7:0] a;
        begin
            addr_ok = (a == 8'h00) || (a == 8'h01) || (a == 8'h02) ||
                      (a == 8'h03) || (a == 8'h04);
        end
    endfunction

    function [15:0] reg_read;
        input [7:0] a;
        begin
            case (a)
                8'h00: reg_read = REG_ID;
                8'h01: reg_read = REG_VERSION;
                8'h02: reg_read = {14'b0, last_cmd_valid, parser_error_seen};
                8'h03: reg_read = cycle_counter[15:0];
                8'h04: reg_read = cycle_counter[31:16];
                default: reg_read = 16'h0000;
            endcase
        end
    endfunction

    // -----------------------------
    // Main sequential logic
    // -----------------------------
    always @(posedge clk) begin
        if (rst) begin
            rx_count          <= 0;
            tx_count          <= 0;
            resp_pending      <= 0;
            tx_valid          <= 0;
            tx_data           <= 0;
            last_status       <= ST_OK;
            parser_error_seen <= 0;
            last_cmd_valid    <= 0;
            cycle_counter     <= 32'd0;
        end else begin
            // Day 16 counter increments every clock
            cycle_counter <= cycle_counter + 1;

            // -------------------------
            // RX capture
            // -------------------------
            if (rx_valid) begin
                case (rx_count)
                    3'd0: b0 <= rx_data;
                    3'd1: b1 <= rx_data;
                    3'd2: b2 <= rx_data;
                    3'd3: b3 <= rx_data;
                    3'd4: b4 <= rx_data;
                    3'd5: b5 <= rx_data;
                endcase

                if (rx_count == 3'd5) begin
                    rx_count <= 0;
                    last_cmd_valid <= 0;

                    if (b0 != SOF) begin
                        last_status <= ST_BADSOF;
                        parser_error_seen <= 1;
                        r0 <= SOF_RESP; r1 <= ST_BADSOF; r2 <= b2; r3 <= 0; r4 <= 0;
                        r5 <= chk(SOF_RESP, ST_BADSOF, b2, 0, 0);
                        resp_pending <= 1;

                    end else if (rx_data != chk(b0,b1,b2,b3,b4)) begin
                        last_status <= ST_BADCHK;
                        parser_error_seen <= 1;
                        r0 <= SOF_RESP; r1 <= ST_BADCHK; r2 <= b2; r3 <= 0; r4 <= 0;
                        r5 <= chk(SOF_RESP, ST_BADCHK, b2, 0, 0);
                        resp_pending <= 1;

                    end else if (b1 == CMD_PING) begin
                        last_status <= ST_OK;
                        last_cmd_valid <= 1;
                        r0 <= SOF_RESP; r1 <= ST_OK; r2 <= 8'h01;
                        r3 <= REG_VERSION[7:0];
                        r4 <= REG_VERSION[15:8];
                        r5 <= chk(SOF_RESP, ST_OK, 8'h01, r3, r4);
                        resp_pending <= 1;

                    end else if (b1 == CMD_RD) begin
                        if (!addr_ok(b2)) begin
                            last_status <= ST_BADADDR;
                            parser_error_seen <= 1;
                            r0 <= SOF_RESP; r1 <= ST_BADADDR; r2 <= b2; r3 <= 0; r4 <= 0;
                            r5 <= chk(SOF_RESP, ST_BADADDR, b2, 0, 0);
                            resp_pending <= 1;
                        end else begin
                            last_status <= ST_OK;
                            last_cmd_valid <= 1;
                            {r4,r3} <= reg_read(b2);
                            r0 <= SOF_RESP; r1 <= ST_OK; r2 <= b2;
                            r5 <= chk(SOF_RESP, ST_OK, b2, r3, r4);
                            resp_pending <= 1;
                        end

                    end else begin
                        last_status <= ST_BADCMD;
                        parser_error_seen <= 1;
                        r0 <= SOF_RESP; r1 <= ST_BADCMD; r2 <= b2; r3 <= 0; r4 <= 0;
                        r5 <= chk(SOF_RESP, ST_BADCMD, b2, 0, 0);
                        resp_pending <= 1;
                    end
                end else begin
                    rx_count <= rx_count + 1;
                end
            end

            // -------------------------
            // TX send
            // -------------------------
            if (resp_pending && tx_ready) begin
                tx_valid <= 1;
                case (tx_count)
                    3'd0: tx_data <= r0;
                    3'd1: tx_data <= r1;
                    3'd2: tx_data <= r2;
                    3'd3: tx_data <= r3;
                    3'd4: tx_data <= r4;
                    3'd5: tx_data <= r5;
                endcase

                if (tx_count == 3'd5) begin
                    tx_count <= 0;
                    resp_pending <= 0;
                    tx_valid <= 0;
                end else begin
                    tx_count <= tx_count + 1;
                end
            end
        end
    end

endmodule

sim/tb_uart_cmd.v
// sim/tb_uart_cmd.v
`timescale 1ns/1ps

module tb_uart_cmd;

    // -----------------------------
    // Clock
    // -----------------------------
    reg clk = 0;
    always #5 clk = ~clk; // 100 MHz

    // -----------------------------
    // DUT signals
    // -----------------------------
    reg        rst;
    reg        rx_valid;
    reg [7:0]  rx_data;

    wire       tx_valid;
    wire [7:0] tx_data;
    reg        tx_ready;

    // -----------------------------
    // DUT instance
    // -----------------------------
    uart_cmd dut (
        .clk(clk),
        .rst(rst),
        .rx_valid(rx_valid),
        .rx_data(rx_data),
        .tx_valid(tx_valid),
        .tx_data(tx_data),
        .tx_ready(tx_ready)
    );

    // -----------------------------
    // Helpers
    // -----------------------------
    function [7:0] chk;
        input [7:0] a,b,c,d,e;
        begin
            chk = a ^ b ^ c ^ d ^ e;
        end
    endfunction

    task send_byte;
        input [7:0] b;
        begin
            @(posedge clk);
            rx_valid <= 1'b1;
            rx_data  <= b;
            @(posedge clk);
            rx_valid <= 1'b0;
            rx_data  <= 8'h00;
        end
    endtask

    task send_frame;
        input [7:0] sof, cmd, addr, d0, d1;
        begin
            send_byte(sof);
            send_byte(cmd);
            send_byte(addr);
            send_byte(d0);
            send_byte(d1);
            send_byte(chk(sof,cmd,addr,d0,d1));
        end
    endtask

    // -----------------------------
    // Test sequence
    // -----------------------------
    initial begin
        // Dump everything (TB + DUT)
        $dumpfile("tb_uart_cmd.vcd");
        $dumpvars(0, tb_uart_cmd);

        // Init
        rst       = 1'b1;
        rx_valid = 1'b0;
        rx_data  = 8'h00;
        tx_ready = 1'b1;

        // Reset
        repeat (5) @(posedge clk);
        rst = 1'b0;

        // -------------------------
        // Day 16 tests
        // -------------------------

        // PING
        send_frame(8'hA5, 8'h03, 8'h00, 8'h00, 8'h00);

        // Read COUNTER_LO (0x03)
        #100;
        send_frame(8'hA5, 8'h02, 8'h03, 8'h00, 8'h00);

        // Read COUNTER_HI (0x04)
        #100;
        send_frame(8'hA5, 8'h02, 8'h04, 8'h00, 8'h00);

        // Wait, then read COUNTER_LO again (should be larger)
        #500;
        send_frame(8'hA5, 8'h02, 8'h03, 8'h00, 8'h00);

        // End
        #500;
        $finish;
    end

endmodule

tb_uart_cmd.vcd
$date
	Sun Jan 04 00:10:14 2026
$end
$version
	Icarus Verilog
$end
$timescale
	1ps
$end
$scope module tb_uart_cmd $end
$var wire 1 ! tx_valid $end
$var wire 8 " tx_data [7:0] $end
$var reg 1 # clk $end
$var reg 1 $ rst $end
$var reg 8 % rx_data [7:0] $end
$var reg 1 & rx_valid $end
$var reg 1 ' tx_ready $end
$scope function chk $end
$var reg 8 ( a [7:0] $end
$var reg 8 ) b [7:0] $end
$var reg 8 * c [7:0] $end
$var reg 8 + d [7:0] $end
$var reg 8 , e [7:0] $end
$upscope $end
$scope module dut $end
$var wire 1 # clk $end
$var wire 1 $ rst $end
$var wire 8 - rx_data [7:0] $end
$var wire 1 & rx_valid $end
$var wire 1 ' tx_ready $end
$var parameter 8 . CMD_PING $end
$var parameter 8 / CMD_RD $end
$var parameter 16 0 REG_ID $end
$var parameter 16 1 REG_VERSION $end
$var parameter 8 2 SOF $end
$var parameter 8 3 SOF_RESP $end
$var parameter 8 4 ST_BADADDR $end
$var parameter 8 5 ST_BADCHK $end
$var parameter 8 6 ST_BADCMD $end
$var parameter 8 7 ST_BADSOF $end
$var parameter 8 8 ST_OK $end
$var reg 8 9 b0 [7:0] $end
$var reg 8 : b1 [7:0] $end
$var reg 8 ; b2 [7:0] $end
$var reg 8 < b3 [7:0] $end
$var reg 8 = b4 [7:0] $end
$var reg 8 > b5 [7:0] $end
$var reg 32 ? cycle_counter [31:0] $end
$var reg 1 @ last_cmd_valid $end
$var reg 8 A last_status [7:0] $end
$var reg 1 B parser_error_seen $end
$var reg 8 C r0 [7:0] $end
$var reg 8 D r1 [7:0] $end
$var reg 8 E r2 [7:0] $end
$var reg 8 F r3 [7:0] $end
$var reg 8 G r4 [7:0] $end
$var reg 8 H r5 [7:0] $end
$var reg 1 I resp_pending $end
$var reg 3 J rx_count [2:0] $end
$var reg 3 K tx_count [2:0] $end
$var reg 8 L tx_data [7:0] $end
$var reg 1 ! tx_valid $end
$scope function addr_ok $end
$var reg 8 M a [7:0] $end
$upscope $end
$scope function chk $end
$var reg 8 N a [7:0] $end
$var reg 8 O b [7:0] $end
$var reg 8 P c [7:0] $end
$var reg 8 Q d [7:0] $end
$var reg 8 R e [7:0] $end
$upscope $end
$scope function reg_read $end
$var reg 8 S a [7:0] $end
$upscope $end
$upscope $end
$scope task send_byte $end
$var reg 8 T b [7:0] $end
$upscope $end
$scope task send_frame $end
$var reg 8 U addr [7:0] $end
$var reg 8 V cmd [7:0] $end
$var reg 8 W d0 [7:0] $end
$var reg 8 X d1 [7:0] $end
$var reg 8 Y sof [7:0] $end
$upscope $end
$upscope $end
$enddefinitions $end
$comment Show the parameter values. $end
$dumpall
b0 8
b11100001 7
b11100011 6
b11100010 5
b11100100 4
b1011010 3
b10100101 2
b10110 1
b100101100110100 0
b10 /
b11 .
$end
#0
$dumpvars
bx Y
bx X
bx W
bx V
bx U
bx T
bx S
bx R
bx Q
bx P
bx O
bx N
bx M
bx L
bx K
bx J
xI
bx H
bx G
bx F
bx E
bx D
bx C
xB
bx A
x@
bx ?
bx >
bx =
bx <
bx ;
bx :
bx 9
b0 -
bx ,
bx +
bx *
bx )
bx (
1'
0&
b0 %
1$
0#
bx "
x!
$end
#5000
b0 ?
0@
0B
b0 A
b0 "
b0 L
0!
0I
b0 K
b0 J
1#
#10000
0#
#15000
1#
#20000
0#
#25000
1#
#30000
0#
#35000
1#
#40000
0#
#45000
b1 ?
b10100101 T
b0 X
b0 W
b0 U
b11 V
b10100101 Y
0$
1#
#50000
0#
#55000
b10 ?
b10100101 %
b10100101 -
1&
1#
#60000
0#
#65000
b0 %
b0 -
0&
b1 J
b10100101 9
b11 ?
b11 T
1#
#70000
0#
#75000
b100 ?
b11 %
b11 -
1&
1#
#80000
0#
#85000
b0 %
b0 -
0&
b10 J
b11 :
b101 ?
b0 T
1#
#90000
0#
#95000
b110 ?
1&
1#
#100000
0#
#105000
0&
b11 J
b0 ;
b111 ?
1#
#110000
0#
#115000
b1000 ?
1&
1#
#120000
0#
#125000
0&
b100 J
b0 <
b1001 ?
1#
#130000
0#
#135000
b1010 ?
1&
1#
#140000
0#
#145000
0&
b101 J
b0 =
b1011 ?
b10100110 T
b10100101 (
b11 )
b0 *
b0 +
b0 ,
1#
#150000
0#
#155000
b1100 ?
b10100110 %
b10100110 -
1&
1#
#160000
0#
#165000
b0 %
b0 -
0&
1I
b0 G
b10110 F
b1 E
b0 D
b1011010 C
1@
b0 J
b10100110 >
b1101 ?
b1011010 N
b0 O
b1 P
bx Q
bx R
1#
#170000
0#
#175000
b1 K
b1011010 "
b1011010 L
1!
b1110 ?
1#
#180000
0#
#185000
b10 K
b0 "
b0 L
b1111 ?
1#
#190000
0#
#195000
b11 K
b1 "
b1 L
b10000 ?
1#
#200000
0#
#205000
b100 K
b10110 "
b10110 L
b10001 ?
1#
#210000
0#
#215000
b101 K
b0 "
b0 L
b10010 ?
1#
#220000
0#
#225000
0!
0I
b0 K
bx "
bx L
b10011 ?
1#
#230000
0#
#235000
b10100 ?
1#
#240000
0#
#245000
b10101 ?
1#
#250000
0#
#255000
b10110 ?
1#
#260000
0#
#265000
b10111 ?
b10100101 %
b10100101 -
1&
1#
b10100101 T
b11 U
b10 V
#270000
0#
#275000
b0 %
b0 -
0&
b1 J
b11000 ?
b10 T
1#
#280000
0#
#285000
b11001 ?
b10 %
b10 -
1&
1#
#290000
0#
#295000
b0 %
b0 -
0&
b10 J
b10 :
b11010 ?
b11 T
1#
#300000
0#
#305000
b11011 ?
b11 %
b11 -
1&
1#
#310000
0#
#315000
b0 %
b0 -
0&
b11 J
b11 ;
b11100 ?
b0 T
1#
#320000
0#
#325000
b11101 ?
1&
1#
#330000
0#
#335000
0&
b100 J
b11110 ?
1#
#340000
0#
#345000
b11111 ?
1&
1#
#350000
0#
#355000
0&
b101 J
b100000 ?
b10100100 T
b10 )
b11 *
1#
#360000
0#
#365000
b100001 ?
b10100100 %
b10100100 -
1&
1#
#370000
0#
#375000
b0 %
b0 -
0&
1I
b1001111 H
b11 E
b100001 F
1@
b0 J
b10100100 >
b100010 ?
b11 S
b11 M
b1011010 N
b0 O
b11 P
b10110 Q
b0 R
1#
#380000
0#
#385000
b1 K
b1011010 "
b1011010 L
1!
b100011 ?
1#
#390000
0#
#395000
b10 K
b0 "
b0 L
b100100 ?
1#
#400000
0#
#405000
b11 K
b11 "
b11 L
b100101 ?
1#
#410000
0#
#415000
b100 K
b100001 "
b100001 L
b100110 ?
1#
#420000
0#
#425000
b101 K
b0 "
b0 L
b100111 ?
1#
#430000
0#
#435000
0!
0I
b0 K
b1001111 "
b1001111 L
b101000 ?
1#
#440000
0#
#445000
b101001 ?
1#
#450000
0#
#455000
b101010 ?
1#
#460000
0#
#465000
b101011 ?
1#
#470000
0#
#475000
b101100 ?
b10100101 %
b10100101 -
1&
1#
b10100101 T
b100 U
#480000
0#
#485000
b0 %
b0 -
0&
b1 J
b101101 ?
b10 T
1#
#490000
0#
#495000
b101110 ?
b10 %
b10 -
1&
1#
#500000
0#
#505000
b0 %
b0 -
0&
b10 J
b101111 ?
b100 T
1#
#510000
0#
#515000
b110000 ?
b100 %
b100 -
1&
1#
#520000
0#
#525000
b0 %
b0 -
0&
b11 J
b100 ;
b110001 ?
b0 T
1#
#530000
0#
#535000
b110010 ?
1&
1#
#540000
0#
#545000
0&
b100 J
b110011 ?
1#
#550000
0#
#555000
b110100 ?
1&
1#
#560000
0#
#565000
0&
b101 J
b110101 ?
b10100011 T
b100 *
1#
#570000
0#
#575000
b110110 ?
b10100011 %
b10100011 -
1&
1#
#580000
0#
#585000
b0 %
b0 -
0&
1I
b1111111 H
b100 E
b0 F
1@
b0 J
b10100011 >
b110111 ?
b100 S
b100 M
b1011010 N
b0 O
b100 P
b100001 Q
1#
#590000
0#
#595000
b1 K
b1011010 "
b1011010 L
1!
b111000 ?
1#
#600000
0#
#605000
b10 K
b0 "
b0 L
b111001 ?
1#
#610000
0#
#615000
b11 K
b100 "
b100 L
b111010 ?
1#
#620000
0#
#625000
b100 K
b0 "
b0 L
b111011 ?
1#
#630000
0#
#635000
b101 K
b111100 ?
1#
#640000
0#
#645000
0!
0I
b0 K
b1111111 "
b1111111 L
b111101 ?
1#
#650000
0#
#655000
b111110 ?
1#
#660000
0#
#665000
b111111 ?
1#
#670000
0#
#675000
b1000000 ?
1#
#680000
0#
#685000
b1000001 ?
1#
#690000
0#
#695000
b1000010 ?
1#
#700000
0#
#705000
b1000011 ?
1#
#710000
0#
#715000
b1000100 ?
1#
#720000
0#
#725000
b1000101 ?
1#
#730000
0#
#735000
b1000110 ?
1#
#740000
0#
#745000
b1000111 ?
1#
#750000
0#
#755000
b1001000 ?
1#
#760000
0#
#765000
b1001001 ?
1#
#770000
0#
#775000
b1001010 ?
1#
#780000
0#
#785000
b1001011 ?
1#
#790000
0#
#795000
b1001100 ?
1#
#800000
0#
#805000
b1001101 ?
1#
#810000
0#
#815000
b1001110 ?
1#
#820000
0#
#825000
b1001111 ?
1#
#830000
0#
#835000
b1010000 ?
1#
#840000
0#
#845000
b1010001 ?
1#
#850000
0#
#855000
b1010010 ?
1#
#860000
0#
#865000
b1010011 ?
1#
#870000
0#
#875000
b1010100 ?
1#
#880000
0#
#885000
b1010101 ?
1#
#890000
0#
#895000
b1010110 ?
1#
#900000
0#
#905000
b1010111 ?
1#
#910000
0#
#915000
b1011000 ?
1#
#920000
0#
#925000
b1011001 ?
1#
#930000
0#
#935000
b1011010 ?
1#
#940000
0#
#945000
b1011011 ?
1#
#950000
0#
#955000
b1011100 ?
1#
#960000
0#
#965000
b1011101 ?
1#
#970000
0#
#975000
b1011110 ?
1#
#980000
0#
#985000
b1011111 ?
1#
#990000
0#
#995000
b1100000 ?
1#
#1000000
0#
#1005000
b1100001 ?
1#
#1010000
0#
#1015000
b1100010 ?
1#
#1020000
0#
#1025000
b1100011 ?
1#
#1030000
0#
#1035000
b1100100 ?
1#
#1040000
0#
#1045000
b1100101 ?
1#
#1050000
0#
#1055000
b1100110 ?
1#
#1060000
0#
#1065000
b1100111 ?
1#
#1070000
0#
#1075000
b1101000 ?
1#
#1080000
0#
#1085000
b1101001 ?
b10100101 %
b10100101 -
1&
1#
b10100101 T
b11 U
#1090000
0#
#1095000
b0 %
b0 -
0&
b1 J
b1101010 ?
b10 T
1#
#1100000
0#
#1105000
b1101011 ?
b10 %
b10 -
1&
1#
#1110000
0#
#1115000
b0 %
b0 -
0&
b10 J
b1101100 ?
b11 T
1#
#1120000
0#
#1125000
b1101101 ?
b11 %
b11 -
1&
1#
#1130000
0#
#1135000
b0 %
b0 -
0&
b11 J
b11 ;
b1101110 ?
b0 T
1#
#1140000
0#
#1145000
b1101111 ?
1&
1#
#1150000
0#
#1155000
0&
b100 J
b1110000 ?
1#
#1160000
0#
#1165000
b1110001 ?
1&
1#
#1170000
0#
#1175000
0&
b101 J
b1110010 ?
b10100100 T
b11 *
1#
#1180000
0#
#1185000
b1110011 ?
b10100100 %
b10100100 -
1&
1#
#1190000
0#
#1195000
b0 %
b0 -
0&
1I
b1011001 H
b11 E
b1110011 F
1@
b0 J
b10100100 >
b1110100 ?
b11 S
b11 M
b1011010 N
b0 O
b11 P
b0 Q
1#
#1200000
0#
#1205000
b1 K
b1011010 "
b1011010 L
1!
b1110101 ?
1#
#1210000
0#
#1215000
b10 K
b0 "
b0 L
b1110110 ?
1#
#1220000
0#
#1225000
b11 K
b11 "
b11 L
b1110111 ?
1#
#1230000
0#
#1235000
b100 K
b1110011 "
b1110011 L
b1111000 ?
1#
#1240000
0#
#1245000
b101 K
b0 "
b0 L
b1111001 ?
1#
#1250000
0#
#1255000
0!
0I
b0 K
b1011001 "
b1011001 L
b1111010 ?
1#
#1260000
0#
#1265000
b1111011 ?
1#
#1270000
0#
#1275000
b1111100 ?
1#
#1280000
0#
#1285000
b1111101 ?
1#
#1290000
0#
#1295000
b1111110 ?
1#
#1300000
0#
#1305000
b1111111 ?
1#
#1310000
0#
#1315000
b10000000 ?
1#
#1320000
0#
#1325000
b10000001 ?
1#
#1330000
0#
#1335000
b10000010 ?
1#
#1340000
0#
#1345000
b10000011 ?
1#
#1350000
0#
#1355000
b10000100 ?
1#
#1360000
0#
#1365000
b10000101 ?
1#
#1370000
0#
#1375000
b10000110 ?
1#
#1380000
0#
#1385000
b10000111 ?
1#
#1390000
0#
#1395000
b10001000 ?
1#
#1400000
0#
#1405000
b10001001 ?
1#
#1410000
0#
#1415000
b10001010 ?
1#
#1420000
0#
#1425000
b10001011 ?
1#
#1430000
0#
#1435000
b10001100 ?
1#
#1440000
0#
#1445000
b10001101 ?
1#
#1450000
0#
#1455000
b10001110 ?
1#
#1460000
0#
#1465000
b10001111 ?
1#
#1470000
0#
#1475000
b10010000 ?
1#
#1480000
0#
#1485000
b10010001 ?
1#
#1490000
0#
#1495000
b10010010 ?
1#
#1500000
0#
#1505000
b10010011 ?
1#
#1510000
0#
#1515000
b10010100 ?
1#
#1520000
0#
#1525000
b10010101 ?
1#
#1530000
0#
#1535000
b10010110 ?
1#
#1540000
0#
#1545000
b10010111 ?
1#
#1550000
0#
#1555000
b10011000 ?
1#
#1560000
0#
#1565000
b10011001 ?
1#
#1570000
0#
#1575000
b10011010 ?
1#
#1580000
0#
#1585000
b10011011 ?
1#
#1590000
0#
#1595000
b10011100 ?
1#
#1600000
0#
#1605000
b10011101 ?
1#
#1610000
0#
#1615000
b10011110 ?
1#
#1620000
0#
#1625000
b10011111 ?
1#
#1630000
0#
#1635000
b10100000 ?
1#
#1640000
0#
#1645000
b10100001 ?
1#
#1650000
0#
#1655000
b10100010 ?
1#
#1660000
0#
#1665000
b10100011 ?
1#
#1670000
0#
#1675000
b10100100 ?
1#
#1680000
0#
#1685000
b10100101 ?
1#
#1690000
0#
#1695000
b10100110 ?
1#
