rtl/uart_cmd.v
// rtl/uart_cmd.v
// Simple UART command interface: PING / RD (and optional WR stub)
// Frame: A5 cmd addr d0 d1 chk
// Resp : 5A status addr d0 d1 chk

module uart_cmd #(
    parameter [15:0] REG_ID      = 16'h4B34,
    parameter [15:0] REG_VERSION = 16'h0015
)(
    input  wire       clk,
    input  wire       rst,          // synchronous reset preferred; ok if async if your design uses it

    // Byte stream in from UART RX
    input  wire       rx_valid,
    input  wire [7:0] rx_data,

    // Byte stream out to UART TX (handshake: tx_ready tells us when we can push next byte)
    output reg        tx_valid,
    output reg  [7:0] tx_data,
    input  wire       tx_ready
);

    // ----------------------------
    // Frame capture (6 bytes)
    // ----------------------------
    reg [2:0]  rx_count;
    reg [7:0]  f0, f1, f2, f3, f4, f5;

    // Status flags (simple, useful in sim)
    reg parser_error_seen;
    reg last_cmd_valid;

    // Last error/status code to report
    reg [7:0] last_status;

    // Response packet bytes
    reg [7:0] r0, r1, r2, r3, r4, r5;

    // TX FSM to send 6 bytes when we have a response ready
    reg [2:0] tx_count;
    reg       resp_pending;

    // Helper: compute XOR checksum
    function [7:0] xor5;
        input [7:0] a,b,c,d,e;
        begin
            xor5 = a ^ b ^ c ^ d ^ e;
        end
    endfunction

    // Register read function
    function [15:0] reg_read;
        input [7:0] addr;
        begin
            case (addr)
                8'h00: reg_read = REG_ID;
                8'h01: reg_read = REG_VERSION;
                8'h02: reg_read = {14'b0, last_cmd_valid, parser_error_seen}; // STATUS
                default: reg_read = 16'h0000; // will be treated as bad addr
            endcase
        end
    endfunction

    // Check if address is valid
    function addr_valid;
        input [7:0] addr;
        begin
            case (addr)
                8'h00, 8'h01, 8'h02: addr_valid = 1'b1;
                default: addr_valid = 1'b0;
            endcase
        end
    endfunction

    // CMD values
    localparam [7:0] CMD_WR   = 8'h01;
    localparam [7:0] CMD_RD   = 8'h02;
    localparam [7:0] CMD_PING = 8'h03;

    // Status codes
    localparam [7:0] ST_OK      = 8'h00;
    localparam [7:0] ST_BADSOF  = 8'hE1;
    localparam [7:0] ST_BADCHK  = 8'hE2;
    localparam [7:0] ST_BADCMD  = 8'hE3;
    localparam [7:0] ST_BADADDR = 8'hE4;

    // ----------------------------
    // RX capture
    // ----------------------------
    always @(posedge clk) begin
        if (rst) begin
            rx_count          <= 3'd0;
            f0 <= 8'd0; f1 <= 8'd0; f2 <= 8'd0; f3 <= 8'd0; f4 <= 8'd0; f5 <= 8'd0;

            parser_error_seen <= 1'b0;
            last_cmd_valid    <= 1'b0;
            last_status       <= ST_OK;

            // TX/response
            tx_valid      <= 1'b0;
            tx_data       <= 8'd0;
            tx_count      <= 3'd0;
            resp_pending  <= 1'b0;

            r0 <= 8'd0; r1 <= 8'd0; r2 <= 8'd0; r3 <= 8'd0; r4 <= 8'd0; r5 <= 8'd0;
        end else begin
            // Default: tx_valid deassert unless we're actively sending
            if (!resp_pending) begin
                tx_valid <= 1'b0;
            end

            // Capture incoming bytes into frame buffer
            if (rx_valid) begin
                case (rx_count)
                    3'd0: f0 <= rx_data;
                    3'd1: f1 <= rx_data;
                    3'd2: f2 <= rx_data;
                    3'd3: f3 <= rx_data;
                    3'd4: f4 <= rx_data;
                    3'd5: f5 <= rx_data;
                endcase

                if (rx_count == 3'd5) begin
                    rx_count <= 3'd0;

                    // We have a full frame now: f0..f4 are previous, f5 is last captured this cycle.
                    // But note: f5 is updated nonblocking above. Use rx_data for the 6th byte.
                    // So reconstruct local wires:
                    //   b0=f0, b1=f1, b2=f2, b3=f3, b4=f4, b5=rx_data

                    // Validate + build response (only if we are not already sending a response)
                    if (!resp_pending) begin
                        // Clear valid flag for this new frame (set if OK)
                        last_cmd_valid <= 1'b0;

                        // Basic checks
                        if (f0 != 8'hA5) begin
                            last_status       <= ST_BADSOF;
                            parser_error_seen <= 1'b1;
                            // Response: error, echo addr if we can (use f2)
                            r0 <= 8'h5A;
                            r1 <= ST_BADSOF;
                            r2 <= f2;
                            r3 <= 8'h00;
                            r4 <= 8'h00;
                            r5 <= xor5(8'h5A, ST_BADSOF, f2, 8'h00, 8'h00);
                            resp_pending <= 1'b1;
                            tx_count <= 3'd0;
                        end else if (rx_data != xor5(f0, f1, f2, f3, f4)) begin
                            last_status       <= ST_BADCHK;
                            parser_error_seen <= 1'b1;
                            r0 <= 8'h5A;
                            r1 <= ST_BADCHK;
                            r2 <= f2;
                            r3 <= 8'h00;
                            r4 <= 8'h00;
                            r5 <= xor5(8'h5A, ST_BADCHK, f2, 8'h00, 8'h00);
                            resp_pending <= 1'b1;
                            tx_count <= 3'd0;
                        end else begin
                            // Command decode
                            if (f1 == CMD_PING) begin
                                last_status    <= ST_OK;
                                last_cmd_valid <= 1'b1;

                                // For PING: return VERSION in data
                                r0 <= 8'h5A;
                                r1 <= ST_OK;
                                r2 <= 8'h01; // pretend "addr=VERSION"
                                r3 <= REG_VERSION[7:0];
                                r4 <= REG_VERSION[15:8];
                                r5 <= xor5(8'h5A, ST_OK, 8'h01, REG_VERSION[7:0], REG_VERSION[15:8]);
                                resp_pending <= 1'b1;
                                tx_count <= 3'd0;

                            end else if (f1 == CMD_RD) begin
                                if (!addr_valid(f2)) begin
                                    last_status       <= ST_BADADDR;
                                    parser_error_seen <= 1'b1;

                                    r0 <= 8'h5A;
                                    r1 <= ST_BADADDR;
                                    r2 <= f2;
                                    r3 <= 8'h00;
                                    r4 <= 8'h00;
                                    r5 <= xor5(8'h5A, ST_BADADDR, f2, 8'h00, 8'h00);
                                    resp_pending <= 1'b1;
                                    tx_count <= 3'd0;
                                end else begin
                                    // read value
                                    begin : rdblk
                                        reg [15:0] v;
                                        v = reg_read(f2);
                                        last_status    <= ST_OK;
                                        last_cmd_valid <= 1'b1;

                                        r0 <= 8'h5A;
                                        r1 <= ST_OK;
                                        r2 <= f2;
                                        r3 <= v[7:0];
                                        r4 <= v[15:8];
                                        r5 <= xor5(8'h5A, ST_OK, f2, v[7:0], v[15:8]);
                                        resp_pending <= 1'b1;
                                        tx_count <= 3'd0;
                                    end
                                end

                            end else if (f1 == CMD_WR) begin
                                // Optional today: treat all WR as bad addr (or later add CONTROL reg)
                                // For Day 15: simplest is reject with BADADDR unless you want CONTROL.
                                last_status       <= ST_BADADDR;
                                parser_error_seen <= 1'b1;

                                r0 <= 8'h5A;
                                r1 <= ST_BADADDR;
                                r2 <= f2;
                                r3 <= 8'h00;
                                r4 <= 8'h00;
                                r5 <= xor5(8'h5A, ST_BADADDR, f2, 8'h00, 8'h00);
                                resp_pending <= 1'b1;
                                tx_count <= 3'd0;

                            end else begin
                                last_status       <= ST_BADCMD;
                                parser_error_seen <= 1'b1;

                                r0 <= 8'h5A;
                                r1 <= ST_BADCMD;
                                r2 <= f2;
                                r3 <= 8'h00;
                                r4 <= 8'h00;
                                r5 <= xor5(8'h5A, ST_BADCMD, f2, 8'h00, 8'h00);
                                resp_pending <= 1'b1;
                                tx_count <= 3'd0;
                            end
                        end
                    end
                end else begin
                    rx_count <= rx_count + 3'd1;
                end
            end

            // ----------------------------
            // TX response sender
            // ----------------------------
            if (resp_pending) begin
                // Only drive tx_valid when we actually have a byte to present
                tx_valid <= 1'b1;

                case (tx_count)
                    3'd0: tx_data <= r0;
                    3'd1: tx_data <= r1;
                    3'd2: tx_data <= r2;
                    3'd3: tx_data <= r3;
                    3'd4: tx_data <= r4;
                    3'd5: tx_data <= r5;
                    default: tx_data <= 8'h00;
                endcase

                // Advance when UART TX accepts the byte
                if (tx_ready) begin
                    if (tx_count == 3'd5) begin
                        tx_count     <= 3'd0;
                        resp_pending <= 1'b0;
                        tx_valid     <= 1'b0;
                    end else begin
                        tx_count <= tx_count + 3'd1;
                    end
                end
            end
        end
    end

endmodule

sim/tb_uart_cmd.v
// sim/tb_uart_cmd.v
`timescale 1ns/1ps

module tb_uart_cmd;

    // -----------------------------
    // Clock
    // -----------------------------
    reg clk = 0;
    always #5 clk = ~clk; // 100 MHz

    // -----------------------------
    // DUT signals
    // -----------------------------
    reg        rst;
    reg        rx_valid;
    reg [7:0]  rx_data;

    wire       tx_valid;
    wire [7:0] tx_data;
    reg        tx_ready;

    // -----------------------------
    // DUT instance
    // -----------------------------
    uart_cmd dut (
        .clk(clk),
        .rst(rst),
        .rx_valid(rx_valid),
        .rx_data(rx_data),
        .tx_valid(tx_valid),
        .tx_data(tx_data),
        .tx_ready(tx_ready)
    );

    // -----------------------------
    // Helpers
    // -----------------------------
    function [7:0] chk;
        input [7:0] a,b,c,d,e;
        begin
            chk = a ^ b ^ c ^ d ^ e;
        end
    endfunction

    task send_byte;
        input [7:0] b;
        begin
            @(posedge clk);
            rx_valid <= 1'b1;
            rx_data  <= b;
            @(posedge clk);
            rx_valid <= 1'b0;
            rx_data  <= 8'h00;
        end
    endtask

    task send_frame;
        input [7:0] sof, cmd, addr, d0, d1;
        begin
            send_byte(sof);
            send_byte(cmd);
            send_byte(addr);
            send_byte(d0);
            send_byte(d1);
            send_byte(chk(sof,cmd,addr,d0,d1));
        end
    endtask

    // -----------------------------
    // Test sequence
    // -----------------------------
    initial begin
        // Dump everything (TB + DUT)
        $dumpfile("tb_uart_cmd.vcd");
        $dumpvars(0, tb_uart_cmd);

        // Init
        rst       = 1'b1;
        rx_valid = 1'b0;
        rx_data  = 8'h00;
        tx_ready = 1'b1;

        // Reset
        repeat (5) @(posedge clk);
        rst = 1'b0;

        // -------------------------
        // Day 16 tests
        // -------------------------

        // PING
        send_frame(8'hA5, 8'h03, 8'h00, 8'h00, 8'h00);

        // Read COUNTER_LO (0x03)
        #100;
        send_frame(8'hA5, 8'h02, 8'h03, 8'h00, 8'h00);

        // Read COUNTER_HI (0x04)
        #100;
        send_frame(8'hA5, 8'h02, 8'h04, 8'h00, 8'h00);

        // Wait, then read COUNTER_LO again (should be larger)
        #500;
        send_frame(8'hA5, 8'h02, 8'h03, 8'h00, 8'h00);

        // End
        #500;
        $finish;
    end

endmodule

tb_uart_cmd.vcd
$date
	Fri Jan 02 23:02:13 2026
$end
$version
	Icarus Verilog
$end
$timescale
	1ps
$end
$scope module tb_uart_cmd $end
$var wire 1 ! tx_valid $end
$var wire 8 " tx_data [7:0] $end
$var reg 1 # clk $end
$var reg 1 $ rst $end
$var reg 8 % rx_data [7:0] $end
$var reg 1 & rx_valid $end
$var reg 1 ' tx_ready $end
$scope function chk $end
$var reg 8 ( a [7:0] $end
$var reg 8 ) b [7:0] $end
$var reg 8 * c [7:0] $end
$var reg 8 + d [7:0] $end
$var reg 8 , e [7:0] $end
$upscope $end
$scope module dut $end
$var wire 1 # clk $end
$var wire 1 $ rst $end
$var wire 8 - rx_data [7:0] $end
$var wire 1 & rx_valid $end
$var wire 1 ' tx_ready $end
$var parameter 8 . CMD_PING $end
$var parameter 8 / CMD_RD $end
$var parameter 8 0 CMD_WR $end
$var parameter 16 1 REG_ID $end
$var parameter 16 2 REG_VERSION $end
$var parameter 8 3 ST_BADADDR $end
$var parameter 8 4 ST_BADCHK $end
$var parameter 8 5 ST_BADCMD $end
$var parameter 8 6 ST_BADSOF $end
$var parameter 8 7 ST_OK $end
$var reg 8 8 f0 [7:0] $end
$var reg 8 9 f1 [7:0] $end
$var reg 8 : f2 [7:0] $end
$var reg 8 ; f3 [7:0] $end
$var reg 8 < f4 [7:0] $end
$var reg 8 = f5 [7:0] $end
$var reg 1 > last_cmd_valid $end
$var reg 8 ? last_status [7:0] $end
$var reg 1 @ parser_error_seen $end
$var reg 8 A r0 [7:0] $end
$var reg 8 B r1 [7:0] $end
$var reg 8 C r2 [7:0] $end
$var reg 8 D r3 [7:0] $end
$var reg 8 E r4 [7:0] $end
$var reg 8 F r5 [7:0] $end
$var reg 1 G resp_pending $end
$var reg 3 H rx_count [2:0] $end
$var reg 3 I tx_count [2:0] $end
$var reg 8 J tx_data [7:0] $end
$var reg 1 ! tx_valid $end
$scope function addr_valid $end
$var reg 8 K addr [7:0] $end
$upscope $end
$scope function reg_read $end
$var reg 8 L addr [7:0] $end
$upscope $end
$scope function xor5 $end
$var reg 8 M a [7:0] $end
$var reg 8 N b [7:0] $end
$var reg 8 O c [7:0] $end
$var reg 8 P d [7:0] $end
$var reg 8 Q e [7:0] $end
$upscope $end
$scope begin rdblk $end
$var reg 16 R v [15:0] $end
$upscope $end
$upscope $end
$scope task send_byte $end
$var reg 8 S b [7:0] $end
$upscope $end
$scope task send_frame $end
$var reg 8 T addr [7:0] $end
$var reg 8 U cmd [7:0] $end
$var reg 8 V d0 [7:0] $end
$var reg 8 W d1 [7:0] $end
$var reg 8 X sof [7:0] $end
$upscope $end
$upscope $end
$enddefinitions $end
$comment Show the parameter values. $end
$dumpall
b0 7
b11100001 6
b11100011 5
b11100010 4
b11100100 3
b10101 2
b100101100110100 1
b1 0
b10 /
b11 .
$end
#0
$dumpvars
bx X
bx W
bx V
bx U
bx T
bx S
bx R
bx Q
bx P
bx O
bx N
bx M
bx L
bx K
bx J
bx I
bx H
xG
bx F
bx E
bx D
bx C
bx B
bx A
x@
bx ?
x>
bx =
bx <
bx ;
bx :
bx 9
bx 8
b0 -
bx ,
bx +
bx *
bx )
bx (
1'
0&
b0 %
1$
0#
bx "
x!
$end
#5000
b0 F
b0 E
b0 D
b0 C
b0 B
b0 A
0G
b0 I
b0 "
b0 J
0!
b0 ?
0>
0@
b0 =
b0 <
b0 ;
b0 :
b0 9
b0 8
b0 H
1#
#10000
0#
#15000
1#
#20000
0#
#25000
1#
#30000
0#
#35000
1#
#40000
0#
#45000
b10100101 S
b0 W
b0 V
b0 T
b11 U
b10100101 X
0$
1#
#50000
0#
#55000
b10100101 %
b10100101 -
1&
1#
#60000
0#
#65000
b0 %
b0 -
0&
b1 H
b10100101 8
b11 S
1#
#70000
0#
#75000
b11 %
b11 -
1&
1#
#80000
0#
#85000
b0 %
b0 -
0&
b10 H
b11 9
b0 S
1#
#90000
0#
#95000
1&
1#
#100000
0#
#105000
0&
b11 H
1#
#110000
0#
#115000
1&
1#
#120000
0#
#125000
0&
b100 H
1#
#130000
0#
#135000
1&
1#
#140000
0#
#145000
0&
b101 H
b10100110 S
b10100101 (
b11 )
b0 *
b0 +
b0 ,
1#
#150000
0#
#155000
b10100110 %
b10100110 -
1&
1#
#160000
0#
#165000
b0 %
b0 -
0&
1G
b1001110 F
b10101 D
b1 C
b1011010 A
1>
b0 H
b10100110 =
b10100101 S
b1 T
b10 U
b1011010 M
b0 N
b1 O
b10101 P
b0 Q
1#
#170000
0#
#175000
b1 I
b1011010 "
b1011010 J
1!
b10100101 %
b10100101 -
1&
1#
#180000
0#
#185000
b0 %
b0 -
0&
b10 I
b0 "
b0 J
b1 H
b10 S
1#
#190000
0#
#195000
b11 I
b1 "
b1 J
b10 %
b10 -
1&
1#
#200000
0#
#205000
b0 %
b0 -
0&
b100 I
b10101 "
b10101 J
b10 H
b10 9
b1 S
1#
#210000
0#
#215000
b101 I
b0 "
b0 J
b1 %
b1 -
1&
1#
#220000
0#
#225000
b0 %
b0 -
0&
0!
0G
b0 I
b1001110 "
b1001110 J
b11 H
b1 :
b0 S
1#
#230000
0#
#235000
1&
1#
#240000
0#
#245000
0&
b100 H
1#
#250000
0#
#255000
1&
1#
#260000
0#
#265000
0&
b101 H
b10100110 S
b10 )
b1 *
1#
#270000
0#
#275000
b10100110 %
b10100110 -
1&
1#
#280000
0#
#285000
1G
b0 %
b0 -
0&
1>
b0 H
b10101 R
b1 L
b10100101 S
b1 K
b1011010 M
b0 N
b10101 P
1#
#290000
0#
#295000
b10100101 %
b10100101 -
1&
b1 I
b1011010 "
b1011010 J
1!
1#
#300000
0#
#305000
b10 I
b0 "
b0 J
b1 H
b0 %
b0 -
0&
b10 S
1#
#310000
0#
#315000
b11 I
b1 "
b1 J
b10 %
b10 -
1&
1#
#320000
0#
#325000
b0 %
b0 -
0&
b100 I
b10101 "
b10101 J
b10 H
b1 S
1#
#330000
0#
#335000
b101 I
b0 "
b0 J
b1 %
b1 -
1&
1#
#340000
0#
#345000
b0 %
b0 -
0&
0!
0G
b0 I
b1001110 "
b1001110 J
b11 H
b0 S
1#
#350000
0#
#355000
1&
1#
#360000
0#
#365000
0&
b100 H
1#
#370000
0#
#375000
1&
1#
#380000
0#
#385000
0&
b101 H
b11111111 S
1#
#390000
0#
#395000
b11111111 %
b11111111 -
1&
1#
#400000
0#
#405000
b0 %
b0 -
0&
1G
b10111001 F
b0 D
b11100010 B
1@
b11100010 ?
0>
b0 H
b11111111 =
b1011010 M
b11100010 N
b0 P
1#
#410000
0#
#415000
b1 I
b1011010 "
b1011010 J
1!
1#
#420000
0#
#425000
b10 I
b11100010 "
b11100010 J
1#
#430000
0#
#435000
b11 I
b1 "
b1 J
1#
#440000
0#
#445000
b100 I
b0 "
b0 J
1#
#450000
0#
#455000
b101 I
1#
#460000
0#
#465000
0!
0G
b0 I
b10111001 "
b10111001 J
1#
