rtl/streamer.v
module streamer (
    input  wire clk,
    input  wire rst,
    input  wire tx_busy,
    output reg  tx_start,
    output reg  [7:0] tx_data
);

    reg [7:0] count;
    reg [2:0] state;

    localparam S_SOF  = 0;
    localparam S_DATA = 1;
    localparam S_EOF  = 2;
    localparam S_DONE = 3;

    always @(posedge clk) begin
        if (rst) begin
            state    <= S_SOF;
            count    <= 0;
            tx_start <= 0;
            tx_data  <= 0;
        end else begin
            tx_start <= 0;

            if (!tx_busy) begin
                case (state)
                    S_SOF: begin
                        tx_data  <= 8'h55;
                        tx_start <= 1;
                        state    <= S_DATA;
                    end

                    S_DATA: begin
                        tx_data  <= count;
                        tx_start <= 1;
                        count    <= count + 1;
                        if (count == 8'hFF)
                            state <= S_EOF;
                    end

                    S_EOF: begin
                        tx_data  <= 8'hAA;
                        tx_start <= 1;
                        state    <= S_DONE;
                    end
                endcase
            end
        end
    end

endmodule

rtl/uart_tx.v
module uart_tx (
    input  wire clk,
    input  wire rst,
    input  wire start,
    input  wire [7:0] data,
    output reg  busy,
    output reg  tx
);

    integer i;
    initial begin
        tx   = 1;
        busy = 0;
    end

    always @(posedge clk) begin
        if (rst) begin
            tx   <= 1;
            busy <= 0;
        end else if (start && !busy) begin
            busy <= 1;

            // START bit
            tx <= 0;

            // send data bits (very slow, for visibility)
            for (i = 0; i < 8; i = i + 1)
                tx <= data[i];

            // STOP bit
            tx <= 1;
            busy <= 0;
        end
    end

endmodule

rtl/top_sim.v
`timescale 1ns/1ps

module top_sim;

    reg clk = 0;
    always #50 clk = ~clk;

    reg rst = 1;

    wire tx;
    wire busy;
    wire tx_start;
    wire [7:0] tx_data;

    uart_tx u_tx (
        .clk(clk),
        .rst(rst),
        .start(tx_start),
        .data(tx_data),
        .busy(busy),
        .tx(tx)
    );

    streamer u_stream (
        .clk(clk),
        .rst(rst),
        .tx_busy(busy),
        .tx_start(tx_start),
        .tx_data(tx_data)
    );

    initial begin
        $dumpfile("sim/wave.vcd");
        $dumpvars(0, top_sim);

        #500;
        rst = 0;

        #100000;
        $finish;
    end

endmodule

sim/wave.vcd
$date
	Mon Feb 09 22:31:00 2026
$end
$version
	Icarus Verilog
$end
$timescale
	1ps
$end
$scope module top_sim $end
$var wire 1 ! tx_start $end
$var wire 8 " tx_data [7:0] $end
$var wire 1 # tx $end
$var wire 1 $ busy $end
$var reg 1 % clk $end
$var reg 1 & rst $end
$scope module u_stream $end
$var wire 1 % clk $end
$var wire 1 & rst $end
$var wire 1 $ tx_busy $end
$var parameter 32 ' S_DATA $end
$var parameter 32 ( S_DONE $end
$var parameter 32 ) S_EOF $end
$var parameter 32 * S_SOF $end
$var reg 8 + count [7:0] $end
$var reg 3 , state [2:0] $end
$var reg 8 - tx_data [7:0] $end
$var reg 1 ! tx_start $end
$upscope $end
$scope module u_tx $end
$var wire 1 % clk $end
$var wire 8 . data [7:0] $end
$var wire 1 & rst $end
$var wire 1 ! start $end
$var reg 1 $ busy $end
$var reg 1 # tx $end
$var integer 32 / i [31:0] $end
$upscope $end
$upscope $end
$enddefinitions $end
$comment Show the parameter values. $end
$dumpall
b0 *
b10 )
b11 (
b1 '
$end
#0
$dumpvars
bx /
bx .
bx -
bx ,
bx +
1&
0%
0$
1#
bx "
x!
$end
#50000
b0 "
b0 -
b0 .
0!
b0 +
b0 ,
1%
#100000
0%
#150000
1%
#200000
0%
#250000
1%
#300000
0%
#350000
1%
#400000
0%
#450000
1%
#500000
0%
0&
#550000
b1 ,
1!
b1010101 "
b1010101 -
b1010101 .
1%
#600000
0%
#650000
1#
0$
b1 +
b0 "
b0 -
b0 .
1!
b1000 /
1%
#700000
0%
#750000
b10 +
b1 "
b1 -
b1 .
1!
1#
0$
b1000 /
1%
#800000
0%
#850000
1#
0$
b11 +
b10 "
b10 -
b10 .
1!
b1000 /
1%
#900000
0%
#950000
b100 +
b11 "
b11 -
b11 .
1!
1#
0$
b1000 /
1%
#1000000
0%
#1050000
1#
0$
b101 +
b100 "
b100 -
b100 .
1!
b1000 /
1%
#1100000
0%
#1150000
b110 +
b101 "
b101 -
b101 .
1!
1#
0$
b1000 /
1%
#1200000
0%
#1250000
1#
0$
b111 +
b110 "
b110 -
b110 .
1!
b1000 /
1%
#1300000
0%
#1350000
b1000 +
b111 "
b111 -
b111 .
1!
1#
0$
b1000 /
1%
#1400000
0%
#1450000
1#
0$
b1001 +
b1000 "
b1000 -
b1000 .
1!
b1000 /
1%
#1500000
0%
#1550000
b1010 +
b1001 "
b1001 -
b1001 .
1!
1#
0$
b1000 /
1%
#1600000
0%
#1650000
1#
0$
b1011 +
b1010 "
b1010 -
b1010 .
1!
b1000 /
1%
#1700000
0%
#1750000
b1100 +
b1011 "
b1011 -
b1011 .
1!
1#
0$
b1000 /
1%
#1800000
0%
#1850000
1#
0$
b1101 +
b1100 "
b1100 -
b1100 .
1!
b1000 /
1%
#1900000
0%
#1950000
b1110 +
b1101 "
b1101 -
b1101 .
1!
1#
0$
b1000 /
1%
#2000000
0%
#2050000
1#
0$
b1111 +
b1110 "
b1110 -
b1110 .
1!
b1000 /
1%
#2100000
0%
#2150000
b10000 +
b1111 "
b1111 -
b1111 .
1!
1#
0$
b1000 /
1%
#2200000
0%
#2250000
1#
0$
b10001 +
b10000 "
b10000 -
b10000 .
1!
b1000 /
1%
#2300000
0%
#2350000
b10010 +
b10001 "
b10001 -
b10001 .
1!
1#
0$
b1000 /
1%
#2400000
0%
#2450000
1#
0$
b10011 +
b10010 "
b10010 -
b10010 .
1!
b1000 /
1%
#2500000
0%
#2550000
b10100 +
b10011 "
b10011 -
b10011 .
1!
1#
0$
b1000 /
1%
#2600000
0%
#2650000
1#
0$
b10101 +
b10100 "
b10100 -
b10100 .
1!
b1000 /
1%
#2700000
0%
#2750000
b10110 +
b10101 "
b10101 -
b10101 .
1!
1#
0$
b1000 /
1%
#2800000
0%
#2850000
1#
0$
b10111 +
b10110 "
b10110 -
b10110 .
1!
b1000 /
1%
#2900000
0%
#2950000
b11000 +
b10111 "
b10111 -
b10111 .
1!
1#
0$
b1000 /
1%
#3000000
0%
#3050000
1#
0$
b11001 +
b11000 "
b11000 -
b11000 .
1!
b1000 /
1%
#3100000
0%
#3150000
b11010 +
b11001 "
b11001 -
b11001 .
1!
1#
0$
b1000 /
1%
#3200000
0%
#3250000
1#
0$
b11011 +
b11010 "
b11010 -
b11010 .
1!
b1000 /
1%
#3300000
0%
#3350000
b11100 +
b11011 "
b11011 -
b11011 .
1!
1#
0$
b1000 /
1%
#3400000
0%
#3450000
1#
0$
b11101 +
b11100 "
b11100 -
b11100 .
1!
b1000 /
1%
#3500000
0%
#3550000
b11110 +
b11101 "
b11101 -
b11101 .
1!
1#
0$
b1000 /
1%
#3600000
0%
#3650000
1#
0$
b11111 +
b11110 "
b11110 -
b11110 .
1!
b1000 /
1%
#3700000
0%
#3750000
b100000 +
b11111 "
b11111 -
b11111 .
1!
1#
0$
b1000 /
1%
#3800000
0%
#3850000
1#
0$
b100001 +
b100000 "
b100000 -
b100000 .
1!
b1000 /
1%
#3900000
0%
#3950000
b100010 +
b100001 "
b100001 -
b100001 .
1!
1#
0$
b1000 /
1%
#4000000
0%
#4050000
1#
0$
b100011 +
b100010 "
b100010 -
b100010 .
1!
b1000 /
1%
#4100000
0%
#4150000
b100100 +
b100011 "
b100011 -
b100011 .
1!
1#
0$
b1000 /
1%
#4200000
0%
#4250000
1#
0$
b100101 +
b100100 "
b100100 -
b100100 .
1!
b1000 /
1%
#4300000
0%
#4350000
b100110 +
b100101 "
b100101 -
b100101 .
1!
1#
0$
b1000 /
1%
#4400000
0%
#4450000
1#
0$
b100111 +
b100110 "
b100110 -
b100110 .
1!
b1000 /
1%
#4500000
0%
#4550000
b101000 +
b100111 "
b100111 -
b100111 .
1!
1#
0$
b1000 /
1%
#4600000
0%
#4650000
1#
0$
b101001 +
b101000 "
b101000 -
b101000 .
1!
b1000 /
1%
#4700000
0%
#4750000
b101010 +
b101001 "
b101001 -
b101001 .
1!
1#
0$
b1000 /
1%
#4800000
0%
#4850000
1#
0$
b101011 +
b101010 "
b101010 -
b101010 .
1!
b1000 /
1%
#4900000
0%
#4950000
b101100 +
b101011 "
b101011 -
b101011 .
1!
1#
0$
b1000 /
1%
#5000000
0%
#5050000
1#
0$
b101101 +
b101100 "
b101100 -
b101100 .
1!
b1000 /
1%
#5100000
0%
#5150000
b101110 +
b101101 "
b101101 -
b101101 .
1!
1#
0$
b1000 /
1%
#5200000
0%
#5250000
1#
0$
b101111 +
b101110 "
b101110 -
b101110 .
1!
b1000 /
1%
#5300000
0%
#5350000
b110000 +
b101111 "
b101111 -
b101111 .
1!
1#
0$
b1000 /
1%
#5400000
0%
#5450000
1#
0$
b110001 +
b110000 "
b110000 -
b110000 .
1!
b1000 /
1%
#5500000
0%
#5550000
b110010 +
b110001 "
b110001 -
b110001 .
1!
1#
0$
b1000 /
1%
#5600000
0%
#5650000
1#
0$
b110011 +
b110010 "
b110010 -
b110010 .
1!
b1000 /
1%
#5700000
0%
#5750000
b110100 +
b110011 "
b110011 -
b110011 .
1!
1#
0$
b1000 /
1%
#5800000
0%
#5850000
1#
0$
b110101 +
b110100 "
b110100 -
b110100 .
1!
b1000 /
1%
#5900000
0%
#5950000
b110110 +
b110101 "
b110101 -
b110101 .
1!
1#
0$
b1000 /
1%
#6000000
0%
#6050000
1#
0$
b110111 +
b110110 "
b110110 -
b110110 .
1!
b1000 /
1%
#6100000
0%
#6150000
b111000 +
b110111 "
b110111 -
b110111 .
1!
1#
0$
b1000 /
1%
#6200000
0%
#6250000
1#
0$
b111001 +
b111000 "
b111000 -
b111000 .
1!
b1000 /
1%
#6300000
0%
#6350000
b111010 +
b111001 "
b111001 -
b111001 .
1!
1#
0$
b1000 /
1%
#6400000
0%
#6450000
1#
0$
b111011 +
b111010 "
b111010 -
b111010 .
1!
b1000 /
1%
#6500000
0%
#6550000
b111100 +
b111011 "
b111011 -
b111011 .
1!
1#
0$
b1000 /
1%
#6600000
0%
#6650000
1#
0$
b111101 +
b111100 "
b111100 -
b111100 .
1!
b1000 /
1%
#6700000
0%
#6750000
b111110 +
b111101 "
b111101 -
b111101 .
1!
1#
0$
b1000 /
1%
#6800000
0%
#6850000
1#
0$
b111111 +
b111110 "
b111110 -
b111110 .
1!
b1000 /
1%
#6900000
0%
#6950000
b1000000 +
b111111 "
b111111 -
b111111 .
1!
1#
0$
b1000 /
1%
#7000000
0%
#7050000
1#
0$
b1000001 +
b1000000 "
b1000000 -
b1000000 .
1!
b1000 /
1%
#7100000
0%
#7150000
b1000010 +
b1000001 "
b1000001 -
b1000001 .
1!
1#
0$
b1000 /
1%
#7200000
0%
#7250000
1#
0$
b1000011 +
b1000010 "
b1000010 -
b1000010 .
1!
b1000 /
1%
#7300000
0%
#7350000
b1000100 +
b1000011 "
b1000011 -
b1000011 .
1!
1#
0$
b1000 /
1%
#7400000
0%
#7450000
1#
0$
b1000101 +
b1000100 "
b1000100 -
b1000100 .
1!
b1000 /
1%
#7500000
0%
#7550000
b1000110 +
b1000101 "
b1000101 -
b1000101 .
1!
1#
0$
b1000 /
1%
#7600000
0%
#7650000
1#
0$
b1000111 +
b1000110 "
b1000110 -
b1000110 .
1!
b1000 /
1%
#7700000
0%
#7750000
b1001000 +
b1000111 "
b1000111 -
b1000111 .
1!
1#
0$
b1000 /
1%
#7800000
0%
#7850000
1#
0$
b1001001 +
b1001000 "
b1001000 -
b1001000 .
1!
b1000 /
1%
#7900000
0%
#7950000
b1001010 +
b1001001 "
b1001001 -
b1001001 .
1!
1#
0$
b1000 /
1%
#8000000
0%
#8050000
1#
0$
b1001011 +
b1001010 "
b1001010 -
b1001010 .
1!
b1000 /
1%
#8100000
0%
#8150000
b1001100 +
b1001011 "
b1001011 -
b1001011 .
1!
1#
0$
b1000 /
1%
#8200000
0%
#8250000
1#
0$
b1001101 +
b1001100 "
b1001100 -
b1001100 .
1!
b1000 /
1%
#8300000
0%
#8350000
b1001110 +
b1001101 "
b1001101 -
b1001101 .
1!
1#
0$
b1000 /
1%
#8400000
0%
#8450000
1#
0$
b1001111 +
b1001110 "
b1001110 -
b1001110 .
1!
b1000 /
1%
#8500000
0%
#8550000
b1010000 +
b1001111 "
b1001111 -
b1001111 .
1!
1#
0$
b1000 /
1%
#8600000
0%
#8650000
1#
0$
b1010001 +
b1010000 "
b1010000 -
b1010000 .
1!
b1000 /
1%
#8700000
0%
#8750000
b1010010 +
b1010001 "
b1010001 -
b1010001 .
1!
1#
0$
b1000 /
1%
#8800000
0%
#8850000
1#
0$
b1010011 +
b1010010 "
b1010010 -
b1010010 .
1!
b1000 /
1%
#8900000
0%
#8950000
b1010100 +
b1010011 "
b1010011 -
b1010011 .
1!
1#
0$
b1000 /
1%
#9000000
0%
#9050000
1#
0$
b1010101 +
b1010100 "
b1010100 -
b1010100 .
1!
b1000 /
1%
#9100000
0%
#9150000
b1010110 +
b1010101 "
b1010101 -
b1010101 .
1!
1#
0$
b1000 /
1%
#9200000
0%
#9250000
1#
0$
b1010111 +
b1010110 "
b1010110 -
b1010110 .
1!
b1000 /
1%
#9300000
0%
#9350000
b1011000 +
b1010111 "
b1010111 -
b1010111 .
1!
1#
0$
b1000 /
1%
#9400000
0%
#9450000
1#
0$
b1011001 +
b1011000 "
b1011000 -
b1011000 .
1!
b1000 /
1%
#9500000
0%
#9550000
b1011010 +
b1011001 "
b1011001 -
b1011001 .
1!
1#
0$
b1000 /
1%
#9600000
0%
#9650000
1#
0$
b1011011 +
b1011010 "
b1011010 -
b1011010 .
1!
b1000 /
1%
#9700000
0%
#9750000
b1011100 +
b1011011 "
b1011011 -
b1011011 .
1!
1#
0$
b1000 /
1%
#9800000
0%
#9850000
1#
0$
b1011101 +
b1011100 "
b1011100 -
b1011100 .
1!
b1000 /
1%
#9900000
0%
#9950000
b1011110 +
b1011101 "
b1011101 -
b1011101 .
1!
1#
0$
b1000 /
1%
#10000000
0%
#10050000
1#
0$
b1011111 +
b1011110 "
b1011110 -
b1011110 .
1!
b1000 /
1%
#10100000
0%
#10150000
b1100000 +
b1011111 "
b1011111 -
b1011111 .
1!
1#
0$
b1000 /
1%
#10200000
0%
#10250000
1#
0$
b1100001 +
b1100000 "
b1100000 -
b1100000 .
1!
b1000 /
1%
#10300000
0%
#10350000
b1100010 +
b1100001 "
b1100001 -
b1100001 .
1!
1#
0$
b1000 /
1%
#10400000
0%
#10450000
1#
0$
b1100011 +
b1100010 "
b1100010 -
b1100010 .
1!
b1000 /
1%
#10500000
0%
#10550000
b1100100 +
b1100011 "
b1100011 -
b1100011 .
1!
1#
0$
b1000 /
1%
#10600000
0%
#10650000
1#
0$
b1100101 +
b1100100 "
b1100100 -
b1100100 .
1!
b1000 /
1%
#10700000
0%
#10750000
b1100110 +
b1100101 "
b1100101 -
b1100101 .
1!
1#
0$
b1000 /
1%
#10800000
0%
#10850000
1#
0$
b1100111 +
b1100110 "
b1100110 -
b1100110 .
1!
b1000 /
1%
#10900000
0%
#10950000
b1101000 +
b1100111 "
b1100111 -
b1100111 .
1!
1#
0$
b1000 /
1%
#11000000
0%
#11050000
1#
0$
b1101001 +
b1101000 "
b1101000 -
b1101000 .
1!
b1000 /
1%
#11100000
0%
#11150000
b1101010 +
b1101001 "
b1101001 -
b1101001 .
1!
1#
0$
b1000 /
1%
#11200000
0%
#11250000
1#
0$
b1101011 +
b1101010 "
b1101010 -
b1101010 .
1!
b1000 /
1%
#11300000
0%
#11350000
b1101100 +
b1101011 "
b1101011 -
b1101011 .
1!
1#
0$
b1000 /
1%
#11400000
0%
#11450000
1#
0$
b1101101 +
b1101100 "
b1101100 -
b1101100 .
1!
b1000 /
1%
#11500000
0%
#11550000
b1101110 +
b1101101 "
b1101101 -
b1101101 .
1!
1#
0$
b1000 /
1%
#11600000
0%
#11650000
1#
0$
b1101111 +
b1101110 "
b1101110 -
b1101110 .
1!
b1000 /
1%
#11700000
0%
#11750000
b1110000 +
b1101111 "
b1101111 -
b1101111 .
1!
1#
0$
b1000 /
1%
#11800000
0%
#11850000
1#
0$
b1110001 +
b1110000 "
b1110000 -
b1110000 .
1!
b1000 /
1%
#11900000
0%
#11950000
b1110010 +
b1110001 "
b1110001 -
b1110001 .
1!
1#
0$
b1000 /
1%
#12000000
0%
#12050000
1#
0$
b1110011 +
b1110010 "
b1110010 -
b1110010 .
1!
b1000 /
1%
#12100000
0%
#12150000
b1110100 +
b1110011 "
b1110011 -
b1110011 .
1!
1#
0$
b1000 /
1%
#12200000
0%
#12250000
1#
0$
b1110101 +
b1110100 "
b1110100 -
b1110100 .
1!
b1000 /
1%
#12300000
0%
#12350000
b1110110 +
b1110101 "
b1110101 -
b1110101 .
1!
1#
0$
b1000 /
1%
#12400000
0%
#12450000
1#
0$
b1110111 +
b1110110 "
b1110110 -
b1110110 .
1!
b1000 /
1%
#12500000
0%
#12550000
b1111000 +
b1110111 "
b1110111 -
b1110111 .
1!
1#
0$
b1000 /
1%
#12600000
0%
#12650000
1#
0$
b1111001 +
b1111000 "
b1111000 -
b1111000 .
1!
b1000 /
1%
#12700000
0%
#12750000
b1111010 +
b1111001 "
b1111001 -
b1111001 .
1!
1#
0$
b1000 /
1%
#12800000
0%
#12850000
1#
0$
b1111011 +
b1111010 "
b1111010 -
b1111010 .
1!
b1000 /
1%
#12900000
0%
#12950000
b1111100 +
b1111011 "
b1111011 -
b1111011 .
1!
1#
0$
b1000 /
1%
#13000000
0%
#13050000
1#
0$
b1111101 +
b1111100 "
b1111100 -
b1111100 .
1!
b1000 /
1%
#13100000
0%
#13150000
b1111110 +
b1111101 "
b1111101 -
b1111101 .
1!
1#
0$
b1000 /
1%
#13200000
0%
#13250000
1#
0$
b1111111 +
b1111110 "
b1111110 -
b1111110 .
1!
b1000 /
1%
#13300000
0%
#13350000
b10000000 +
b1111111 "
b1111111 -
b1111111 .
1!
1#
0$
b1000 /
1%
#13400000
0%
#13450000
1#
0$
b10000001 +
b10000000 "
b10000000 -
b10000000 .
1!
b1000 /
1%
#13500000
0%
#13550000
b10000010 +
b10000001 "
b10000001 -
b10000001 .
1!
1#
0$
b1000 /
1%
#13600000
0%
#13650000
1#
0$
b10000011 +
b10000010 "
b10000010 -
b10000010 .
1!
b1000 /
1%
#13700000
0%
#13750000
b10000100 +
b10000011 "
b10000011 -
b10000011 .
1!
1#
0$
b1000 /
1%
#13800000
0%
#13850000
1#
0$
b10000101 +
b10000100 "
b10000100 -
b10000100 .
1!
b1000 /
1%
#13900000
0%
#13950000
b10000110 +
b10000101 "
b10000101 -
b10000101 .
1!
1#
0$
b1000 /
1%
#14000000
0%
#14050000
1#
0$
b10000111 +
b10000110 "
b10000110 -
b10000110 .
1!
b1000 /
1%
#14100000
0%
#14150000
b10001000 +
b10000111 "
b10000111 -
b10000111 .
1!
1#
0$
b1000 /
1%
#14200000
0%
#14250000
1#
0$
b10001001 +
b10001000 "
b10001000 -
b10001000 .
1!
b1000 /
1%
#14300000
0%
#14350000
b10001010 +
b10001001 "
b10001001 -
b10001001 .
1!
1#
0$
b1000 /
1%
#14400000
0%
#14450000
1#
0$
b10001011 +
b10001010 "
b10001010 -
b10001010 .
1!
b1000 /
1%
#14500000
0%
#14550000
b10001100 +
b10001011 "
b10001011 -
b10001011 .
1!
1#
0$
b1000 /
1%
#14600000
0%
#14650000
1#
0$
b10001101 +
b10001100 "
b10001100 -
b10001100 .
1!
b1000 /
1%
#14700000
0%
#14750000
b10001110 +
b10001101 "
b10001101 -
b10001101 .
1!
1#
0$
b1000 /
1%
#14800000
0%
#14850000
1#
0$
b10001111 +
b10001110 "
b10001110 -
b10001110 .
1!
b1000 /
1%
#14900000
0%
#14950000
b10010000 +
b10001111 "
b10001111 -
b10001111 .
1!
1#
0$
b1000 /
1%
#15000000
0%
#15050000
1#
0$
b10010001 +
b10010000 "
b10010000 -
b10010000 .
1!
b1000 /
1%
#15100000
0%
#15150000
b10010010 +
b10010001 "
b10010001 -
b10010001 .
1!
1#
0$
b1000 /
1%
#15200000
0%
#15250000
1#
0$
b10010011 +
b10010010 "
b10010010 -
b10010010 .
1!
b1000 /
1%
#15300000
0%
#15350000
b10010100 +
b10010011 "
b10010011 -
b10010011 .
1!
1#
0$
b1000 /
1%
#15400000
0%
#15450000
1#
0$
b10010101 +
b10010100 "
b10010100 -
b10010100 .
1!
b1000 /
1%
#15500000
0%
#15550000
b10010110 +
b10010101 "
b10010101 -
b10010101 .
1!
1#
0$
b1000 /
1%
#15600000
0%
#15650000
1#
0$
b10010111 +
b10010110 "
b10010110 -
b10010110 .
1!
b1000 /
1%
#15700000
0%
#15750000
b10011000 +
b10010111 "
b10010111 -
b10010111 .
1!
1#
0$
b1000 /
1%
#15800000
0%
#15850000
1#
0$
b10011001 +
b10011000 "
b10011000 -
b10011000 .
1!
b1000 /
1%
#15900000
0%
#15950000
b10011010 +
b10011001 "
b10011001 -
b10011001 .
1!
1#
0$
b1000 /
1%
#16000000
0%
#16050000
1#
0$
b10011011 +
b10011010 "
b10011010 -
b10011010 .
1!
b1000 /
1%
#16100000
0%
#16150000
b10011100 +
b10011011 "
b10011011 -
b10011011 .
1!
1#
0$
b1000 /
1%
#16200000
0%
#16250000
1#
0$
b10011101 +
b10011100 "
b10011100 -
b10011100 .
1!
b1000 /
1%
#16300000
0%
#16350000
b10011110 +
b10011101 "
b10011101 -
b10011101 .
1!
1#
0$
b1000 /
1%
#16400000
0%
#16450000
1#
0$
b10011111 +
b10011110 "
b10011110 -
b10011110 .
1!
b1000 /
1%
#16500000
0%
#16550000
b10100000 +
b10011111 "
b10011111 -
b10011111 .
1!
1#
0$
b1000 /
1%
#16600000
0%
#16650000
1#
0$
b10100001 +
b10100000 "
b10100000 -
b10100000 .
1!
b1000 /
1%
#16700000
0%
#16750000
b10100010 +
b10100001 "
b10100001 -
b10100001 .
1!
1#
0$
b1000 /
1%
#16800000
0%
#16850000
1#
0$
b10100011 +
b10100010 "
b10100010 -
b10100010 .
1!
b1000 /
1%
#16900000
0%
#16950000
b10100100 +
b10100011 "
b10100011 -
b10100011 .
1!
1#
0$
b1000 /
1%
#17000000
0%
#17050000
1#
0$
b10100101 +
b10100100 "
b10100100 -
b10100100 .
1!
b1000 /
1%
#17100000
0%
#17150000
b10100110 +
b10100101 "
b10100101 -
b10100101 .
1!
1#
0$
b1000 /
1%
#17200000
0%
#17250000
1#
0$
b10100111 +
b10100110 "
b10100110 -
b10100110 .
1!
b1000 /
1%
#17300000
0%
#17350000
b10101000 +
b10100111 "
b10100111 -
b10100111 .
1!
1#
0$
b1000 /
1%
#17400000
0%
#17450000
1#
0$
b10101001 +
b10101000 "
b10101000 -
b10101000 .
1!
b1000 /
1%
#17500000
0%
#17550000
b10101010 +
b10101001 "
b10101001 -
b10101001 .
1!
1#
0$
b1000 /
1%
#17600000
0%
#17650000
1#
0$
b10101011 +
b10101010 "
b10101010 -
b10101010 .
1!
b1000 /
1%
#17700000
0%
#17750000
b10101100 +
b10101011 "
b10101011 -
b10101011 .
1!
1#
0$
b1000 /
1%
#17800000
0%
#17850000
1#
0$
b10101101 +
b10101100 "
b10101100 -
b10101100 .
1!
b1000 /
1%
#17900000
0%
#17950000
b10101110 +
b10101101 "
b10101101 -
b10101101 .
1!
1#
0$
b1000 /
1%
#18000000
0%
#18050000
1#
0$
b10101111 +
b10101110 "
b10101110 -
b10101110 .
1!
b1000 /
1%
#18100000
0%
#18150000
b10110000 +
b10101111 "
b10101111 -
b10101111 .
1!
1#
0$
b1000 /
1%
#18200000
0%
#18250000
1#
0$
b10110001 +
b10110000 "
b10110000 -
b10110000 .
1!
b1000 /
1%
#18300000
0%
#18350000
b10110010 +
b10110001 "
b10110001 -
b10110001 .
1!
1#
0$
b1000 /
1%
#18400000
0%
#18450000
1#
0$
b10110011 +
b10110010 "
b10110010 -
b10110010 .
1!
b1000 /
1%
#18500000
0%
#18550000
b10110100 +
b10110011 "
b10110011 -
b10110011 .
1!
1#
0$
b1000 /
1%
#18600000
0%
#18650000
1#
0$
b10110101 +
b10110100 "
b10110100 -
b10110100 .
1!
b1000 /
1%
#18700000
0%
#18750000
b10110110 +
b10110101 "
b10110101 -
b10110101 .
1!
1#
0$
b1000 /
1%
#18800000
0%
#18850000
1#
0$
b10110111 +
b10110110 "
b10110110 -
b10110110 .
1!
b1000 /
1%
#18900000
0%
#18950000
b10111000 +
b10110111 "
b10110111 -
b10110111 .
1!
1#
0$
b1000 /
1%
#19000000
0%
#19050000
1#
0$
b10111001 +
b10111000 "
b10111000 -
b10111000 .
1!
b1000 /
1%
#19100000
0%
#19150000
b10111010 +
b10111001 "
b10111001 -
b10111001 .
1!
1#
0$
b1000 /
1%
#19200000
0%
#19250000
1#
0$
b10111011 +
b10111010 "
b10111010 -
b10111010 .
1!
b1000 /
1%
#19300000
0%
#19350000
b10111100 +
b10111011 "
b10111011 -
b10111011 .
1!
1#
0$
b1000 /
1%
#19400000
0%
#19450000
1#
0$
b10111101 +
b10111100 "
b10111100 -
b10111100 .
1!
b1000 /
1%
#19500000
0%
#19550000
b10111110 +
b10111101 "
b10111101 -
b10111101 .
1!
1#
0$
b1000 /
1%
#19600000
0%
#19650000
1#
0$
b10111111 +
b10111110 "
b10111110 -
b10111110 .
1!
b1000 /
1%
#19700000
0%
#19750000
b11000000 +
b10111111 "
b10111111 -
b10111111 .
1!
1#
0$
b1000 /
1%
#19800000
0%
#19850000
1#
0$
b11000001 +
b11000000 "
b11000000 -
b11000000 .
1!
b1000 /
1%
#19900000
0%
#19950000
b11000010 +
b11000001 "
b11000001 -
b11000001 .
1!
1#
0$
b1000 /
1%
#20000000
0%
#20050000
1#
0$
b11000011 +
b11000010 "
b11000010 -
b11000010 .
1!
b1000 /
1%
#20100000
0%
#20150000
b11000100 +
b11000011 "
b11000011 -
b11000011 .
1!
1#
0$
b1000 /
1%
#20200000
0%
#20250000
1#
0$
b11000101 +
b11000100 "
b11000100 -
b11000100 .
1!
b1000 /
1%
#20300000
0%
#20350000
b11000110 +
b11000101 "
b11000101 -
b11000101 .
1!
1#
0$
b1000 /
1%
#20400000
0%
#20450000
1#
0$
b11000111 +
b11000110 "
b11000110 -
b11000110 .
1!
b1000 /
1%
#20500000
0%
#20550000
b11001000 +
b11000111 "
b11000111 -
b11000111 .
1!
1#
0$
b1000 /
1%
#20600000
0%
#20650000
1#
0$
b11001001 +
b11001000 "
b11001000 -
b11001000 .
1!
b1000 /
1%
#20700000
0%
#20750000
b11001010 +
b11001001 "
b11001001 -
b11001001 .
1!
1#
0$
b1000 /
1%
#20800000
0%
#20850000
1#
0$
b11001011 +
b11001010 "
b11001010 -
b11001010 .
1!
b1000 /
1%
#20900000
0%
#20950000
b11001100 +
b11001011 "
b11001011 -
b11001011 .
1!
1#
0$
b1000 /
1%
#21000000
0%
#21050000
1#
0$
b11001101 +
b11001100 "
b11001100 -
b11001100 .
1!
b1000 /
1%
#21100000
0%
#21150000
b11001110 +
b11001101 "
b11001101 -
b11001101 .
1!
1#
0$
b1000 /
1%
#21200000
0%
#21250000
1#
0$
b11001111 +
b11001110 "
b11001110 -
b11001110 .
1!
b1000 /
1%
#21300000
0%
#21350000
b11010000 +
b11001111 "
b11001111 -
b11001111 .
1!
1#
0$
b1000 /
1%
#21400000
0%
#21450000
1#
0$
b11010001 +
b11010000 "
b11010000 -
b11010000 .
1!
b1000 /
1%
#21500000
0%
#21550000
b11010010 +
b11010001 "
b11010001 -
b11010001 .
1!
1#
0$
b1000 /
1%
#21600000
0%
#21650000
1#
0$
b11010011 +
b11010010 "
b11010010 -
b11010010 .
1!
b1000 /
1%
#21700000
0%
#21750000
b11010100 +
b11010011 "
b11010011 -
b11010011 .
1!
1#
0$
b1000 /
1%
#21800000
0%
#21850000
1#
0$
b11010101 +
b11010100 "
b11010100 -
b11010100 .
1!
b1000 /
1%
#21900000
0%
#21950000
b11010110 +
b11010101 "
b11010101 -
b11010101 .
1!
1#
0$
b1000 /
1%
#22000000
0%
#22050000
1#
0$
b11010111 +
b11010110 "
b11010110 -
b11010110 .
1!
b1000 /
1%
#22100000
0%
#22150000
b11011000 +
b11010111 "
b11010111 -
b11010111 .
1!
1#
0$
b1000 /
1%
#22200000
0%
#22250000
1#
0$
b11011001 +
b11011000 "
b11011000 -
b11011000 .
1!
b1000 /
1%
#22300000
0%
#22350000
b11011010 +
b11011001 "
b11011001 -
b11011001 .
1!
1#
0$
b1000 /
1%
#22400000
0%
#22450000
1#
0$
b11011011 +
b11011010 "
b11011010 -
b11011010 .
1!
b1000 /
1%
#22500000
0%
#22550000
b11011100 +
b11011011 "
b11011011 -
b11011011 .
1!
1#
0$
b1000 /
1%
#22600000
0%
#22650000
1#
0$
b11011101 +
b11011100 "
b11011100 -
b11011100 .
1!
b1000 /
1%
#22700000
0%
#22750000
b11011110 +
b11011101 "
b11011101 -
b11011101 .
1!
1#
0$
b1000 /
1%
#22800000
0%
#22850000
1#
0$
b11011111 +
b11011110 "
b11011110 -
b11011110 .
1!
b1000 /
1%
#22900000
0%
#22950000
b11100000 +
b11011111 "
b11011111 -
b11011111 .
1!
1#
0$
b1000 /
1%
#23000000
0%
#23050000
1#
0$
b11100001 +
b11100000 "
b11100000 -
b11100000 .
1!
b1000 /
1%
#23100000
0%
#23150000
b11100010 +
b11100001 "
b11100001 -
b11100001 .
1!
1#
0$
b1000 /
1%
#23200000
0%
#23250000
1#
0$
b11100011 +
b11100010 "
b11100010 -
b11100010 .
1!
b1000 /
1%
#23300000
0%
#23350000
b11100100 +
b11100011 "
b11100011 -
b11100011 .
1!
1#
0$
b1000 /
1%
#23400000
0%
